setuptools_ext.py
setuptools_ext-0.9.dist-info/LICENSE
setuptools_ext-0.9.dist-info/METADATA
setuptools_ext-0.9.dist-info/WHEEL
setuptools_ext-0.9.dist-info/top_level.txt
setuptools_ext-0.9.dist-info/RECORD